[
    {
        "nome": "Pablo",
        "email": "vinicius@lco.com",
        "hash": "$2a$10$paCPKI51WIVPFJA5X4cApO8nLg4ohTzHpealZxvH3uFpm0zZUlCfa",
        "id": null
    },
    {
        "nome": "vinicius@lco.com",
        "email": "vinicius@lco.com",
        "hash": "$2a$10$rEqzwbR4XmviANLcGbpdVufklsfgqTyMQ0W4WXNtcnnwDbhV/VLHq",
        "id": 1
    },
    {
        "nome": "34",
        "email": "vinicius@lco.com",
        "hash": "$2a$10$GE1T7QpWe3V1dE4EcfvZ8e6KX2dTYu/uajdYVr/DB5daQu9.qUa.u",
        "id": 2
    }
]